tests/__init__.py
tests/test_e2e.py
tests/test_tools.py
tests/engine/__init__.py
tests/engine/test_engine.py
tests/engine/test_generation.py
tests/engine/test_parsedfile.py
tests/engine/test_resourcemodel.py
tests/parser/__init__.py
tests/parser/test_parserfactory.py
tests/parser/test_yamlparser.py
tests/parser/dsl_parser/__init__.py
tests/parser/dsl_parser/test_ast.py
tests/parser/dsl_parser/test_dslparser.py
tests/parser/dsl_parser/test_lexer.py
tests/parser/dsl_parser/test_token.py
tests/parser/dsl_parser/test_tokenparser.py
tests/repository/__init__.py
tests/repository/test_github_repository.py
tests/repository/test_local_repository.py
thipster/__init__.py
thipster/helpers.py
thipster/auth/__init__.py
thipster/auth/google.py
thipster/engine/__init__.py
thipster/engine/engine.py
thipster/engine/exceptions.py
thipster/engine/i_auth.py
thipster/engine/i_parser.py
thipster/engine/i_repository.py
thipster/engine/i_terraform.py
thipster/engine/parsed_file.py
thipster/engine/resource_model.py
thipster/parser/__init__.py
thipster/parser/exceptions.py
thipster/parser/parser_factory.py
thipster/parser/yaml_parser.py
thipster/parser/dsl_parser/__init__.py
thipster/parser/dsl_parser/ast.py
thipster/parser/dsl_parser/exceptions.py
thipster/parser/dsl_parser/interpreter.py
thipster/parser/dsl_parser/lexer.py
thipster/parser/dsl_parser/lexer_position.py
thipster/parser/dsl_parser/parser.py
thipster/parser/dsl_parser/token.py
thipster/parser/dsl_parser/token_parser.py
thipster/repository/__init__.py
thipster/repository/exceptions.py
thipster/repository/github.py
thipster/repository/json.py
thipster/repository/local.py
thipster/terraform/__init__.py
thipster/terraform/cdk.py
thipster/terraform/exceptions.py
thipster-0.23.15.dist-info/LICENSE
thipster-0.23.15.dist-info/METADATA
thipster-0.23.15.dist-info/WHEEL
thipster-0.23.15.dist-info/top_level.txt
thipster-0.23.15.dist-info/RECORD
