Metadata-Version: 2.1
Name: thipster
Version: 0.23.15
Summary: THipster is a tool dedicated to simplifying the difficulty associated with writing Terraform files. It allows users to write infrastructure as code in a simplified format, using either YAML (with JINJA) or the dedicated Thipster DSL.
Home-page: https://github.com/THipster/THipster
Download-URL: https://github.com/THipster/THipster.git
Keywords: thipster,terraform,infrastructure,infrastructure-as-code,iac,generator,dsl,yaml
Classifier: Development Status :: 1 - Planning
Classifier: Programming Language :: Python :: 3.11
Classifier: License :: OSI Approved :: MIT License
Classifier: Operating System :: OS Independent
License-File: LICENSE
Requires-Dist: cdktf ==0.17.3
Requires-Dist: Jinja2 ==3.1.2
Requires-Dist: PyYAML ==6.0.1
Requires-Dist: requests ==2.31.0
